doublecloud/__init__.py
doublecloud/_auth_fabric.py
doublecloud/_auth_plugin.py
doublecloud/_backoff.py
doublecloud/_channels.py
doublecloud/_consts.py
doublecloud/_operation_waiter.py
doublecloud/_retry_interceptor.py
doublecloud/_sdk.py
doublecloud/operations.py
doublecloud/_wrappers/__init__.py
doublecloud/_wrappers/clickhouse/__init__.py
doublecloud/_wrappers/kafka/__init__.py
doublecloud/access/__init__.py
doublecloud/access/v1/__init__.py
doublecloud/access/v1/access_pb2.py
doublecloud/access/v1/access_pb2.pyi
doublecloud/access/v1/access_pb2_grpc.py
doublecloud/airflow/__init__.py
doublecloud/airflow/v1/__init__.py
doublecloud/airflow/v1/cluster_pb2.py
doublecloud/airflow/v1/cluster_pb2.pyi
doublecloud/airflow/v1/cluster_pb2_grpc.py
doublecloud/airflow/v1/cluster_service_pb2.py
doublecloud/airflow/v1/cluster_service_pb2.pyi
doublecloud/airflow/v1/cluster_service_pb2_grpc.py
doublecloud/airflow/v1/operation_service_pb2.py
doublecloud/airflow/v1/operation_service_pb2.pyi
doublecloud/airflow/v1/operation_service_pb2_grpc.py
doublecloud/clickhouse/__init__.py
doublecloud/clickhouse/v1/__init__.py
doublecloud/clickhouse/v1/backup_pb2.py
doublecloud/clickhouse/v1/backup_pb2.pyi
doublecloud/clickhouse/v1/backup_pb2_grpc.py
doublecloud/clickhouse/v1/backup_service_pb2.py
doublecloud/clickhouse/v1/backup_service_pb2.pyi
doublecloud/clickhouse/v1/backup_service_pb2_grpc.py
doublecloud/clickhouse/v1/cluster_pb2.py
doublecloud/clickhouse/v1/cluster_pb2.pyi
doublecloud/clickhouse/v1/cluster_pb2_grpc.py
doublecloud/clickhouse/v1/cluster_service_pb2.py
doublecloud/clickhouse/v1/cluster_service_pb2.pyi
doublecloud/clickhouse/v1/cluster_service_pb2_grpc.py
doublecloud/clickhouse/v1/config_pb2.py
doublecloud/clickhouse/v1/config_pb2.pyi
doublecloud/clickhouse/v1/config_pb2_grpc.py
doublecloud/clickhouse/v1/operation_service_pb2.py
doublecloud/clickhouse/v1/operation_service_pb2.pyi
doublecloud/clickhouse/v1/operation_service_pb2_grpc.py
doublecloud/clickhouse/v1/user_pb2.py
doublecloud-0.14.0.dist-info/LICENSE
doublecloud-0.14.0.dist-info/METADATA
doublecloud-0.14.0.dist-info/WHEEL
doublecloud-0.14.0.dist-info/top_level.txt
doublecloud-0.14.0.dist-info/RECORD
