Metadata-Version: 2.1
Name: doublecloud
Version: 0.14.0
Summary: The Double.Cloud official SDK
Home-page: https://github.com/doublecloud/python-sdk
Author: DoubleCloud GmbH
Author-email: support@double.cloud
License: Apache License 2.0
Classifier: Programming Language :: Python
Classifier: Programming Language :: Python :: 3
Classifier: Programming Language :: Python :: 3.9
Classifier: Programming Language :: Python :: 3.10
Classifier: Programming Language :: Python :: 3.11
Classifier: Programming Language :: Python :: 3.12
License-File: LICENSE
Requires-Dist: cryptography>=39.0.2
Requires-Dist: grpcio>=1.51.3
Requires-Dist: protobuf==4.25.3
Requires-Dist: grpcio-tools>=1.51.3
Requires-Dist: googleapis-common-protos>=1.58.0
Requires-Dist: pyjwt>=2.6.0
Requires-Dist: requests>=2.28.2
Requires-Dist: six>=1.16.0
